shortcut_mcp/__init__.py
shortcut_mcp/__main__.py
shortcut_mcp/cli.py
shortcut_mcp/server.py
shortcut_mcp-0.2.3.dist-info/METADATA
shortcut_mcp-0.2.3.dist-info/WHEEL
shortcut_mcp-0.2.3.dist-info/entry_points.txt
shortcut_mcp-0.2.3.dist-info/license_files/LICENSE
shortcut_mcp-0.2.3.dist-info/RECORD
