Metadata-Version: 2.1
Name: shortcut-mcp
Version: 0.2.3
Summary: A Model Context Protocol (MCP) server for interacting with Shortcut
Project-URL: Bug Tracker, https://github.com/idyll/shortcut-mcp/issues
Project-URL: Homepage, https://github.com/idyll/shortcut-mcp
Author: Mark Madsen, Antonio Lorusso
License: MIT
Requires-Python: >=3.12
Requires-Dist: httpx
Requires-Dist: mcp
Requires-Dist: python-dotenv
Provides-Extra: dev
Requires-Dist: pylint>=3.3.2; extra == 'dev'
Provides-Extra: test
Requires-Dist: pytest-asyncio>=0.21.0; extra == 'test'
Requires-Dist: pytest-cov>=4.0.0; extra == 'test'
Requires-Dist: pytest>=7.0.0; extra == 'test'
